Data_Access_Layer-1.1.data/scripts/Manexercise.py
Data_Access_Layer-1.1.dist-info/METADATA
Data_Access_Layer-1.1.dist-info/RECORD
Data_Access_Layer-1.1.dist-info/WHEEL
Data_Access_Layer-1.1.dist-info/top_level.txt
data_access_layer/__init__.py
data_access_layer/data_access_layer.py
